{
    "analysis": [
        {
            "config": {
                "different_template": "iffail",
                "ei_out": false,
                "invariants": "none",
                "lib": "ppl",
                "pe_modes": [
                    4
                ],
                "pe_times": 0,
                "scc_depth": 5,
                "simplify_constraints": true,
                "termination": [
                    "lrf_pr"
                ],
                "verbosity": 0
            },
            "cputime": 5.523474,
            "date": "2018-09-06T21:44:28.925969",
            "memory": 49152,
            "output": "NOT FOUND ",
            "status": "Unknown"
        },
        {
            "config": {
                "different_template": "iffail",
                "ei_out": false,
                "invariants": "none",
                "lib": "ppl",
                "pe_modes": [
                    4
                ],
                "pe_times": 0,
                "scc_depth": 5,
                "simplify_constraints": true,
                "termination": [
                    "qnlrfv1_1_1"
                ],
                "verbosity": 0
            },
            "cputime": 8.12524,
            "date": "2018-09-06T21:44:42.934744",
            "memory": 1900,
            "output": "FOUND:\nl4: < < x3 - x4 + 1 > >\nl14: < <  - x4 + x7 - 1 >, <  - x4 + x7 - 1 >, <  - x4 + x6 - 1 > >\nl0: < <  - x4 + x6 > >\nl7: < <  - x4 + x6 - 1 >, < x3 - x5 > >\nl11: < <  - x4 + x7 >, <  - x4 + x7 >, <  - x4 + x6 > >\nl2: < <  - x4 + x6 > >\nl9: < <  - x4 + x6 > >\nl13: < <  - x4 + x7 - 1 >, <  - x4 + x7 - 1 >, <  - x4 + x6 - 1 > >\nl8: < <  - x4 + x6 - 1 >, < x3 - x5 > >\nl15: < <  - x4 + x7 >, <  - x4 + x7 >, <  - x4 + x6 - 1 > >\nl3: < < x3 - x4 > >\nl10: < <  - x4 + x6 > >\nl5: < < x3 - x4 + 1 > >\nl6: < <  - x4 + x6 - 1 >, < x3 - x5 - 1 > >\nl12: < <  - x4 + x7 >, <  - x4 + x7 >, <  - x4 + x6 > >\n",
            "status": "Terminate"
        },
        {
            "config": {
                "different_template": "iffail",
                "ei_out": false,
                "invariants": "none",
                "lib": "ppl",
                "pe_modes": [
                    4
                ],
                "pe_times": 0,
                "scc_depth": 5,
                "simplify_constraints": true,
                "termination": [
                    "qnlrfv1_2_2"
                ],
                "verbosity": 0
            },
            "cputime": 8.141511999999997,
            "date": "2018-09-06T21:44:56.885750",
            "memory": 5516,
            "output": "FOUND:\nl4: < < x3 - x4, x3 - x4 > >\nl14: < <  - x4 + x6 - 1, 0 > >\nl0: < <  - x4 + x6, 0 > >\nl7: < <  - x4 + x6 - 1, 0 >, < x3 - x5, 0 > >\nl11: < <  - x4 + x6, 0 > >\nl2: < <  - x4 + x6, 0 > >\nl9: < <  - x4 + x6, 0 > >\nl13: < <  - x4 + x6 - 1, 0 > >\nl8: < <  - x4 + x6 - 1, 0 >, < x3 - x5 - 1, x3 - x5 - 1 > >\nl15: < <  - x4 + x6 - 1, 0 > >\nl3: < < x3 - x4, 0 > >\nl10: < <  - x4 + x6, 0 > >\nl5: < < x3 - x4, x3 - x4 > >\nl6: < <  - x4 + x6 - 1, 0 >, < x3 - x5 - 1, 0 > >\nl12: < <  - x4 + x6 - 1,  - x4 + x6 - 1 > >\n",
            "status": "Terminate"
        },
        {
            "config": {
                "different_template": "iffail",
                "ei_out": false,
                "invariants": "interval",
                "lib": "ppl",
                "pe_modes": [
                    4
                ],
                "pe_times": 0,
                "scc_depth": 5,
                "simplify_constraints": true,
                "termination": [
                    "lrf_pr"
                ],
                "verbosity": 0
            },
            "cputime": 5.742611999999999,
            "date": "2018-09-06T21:45:06.094562",
            "memory": 0,
            "output": "NOT FOUND ",
            "status": "Unknown"
        },
        {
            "config": {
                "different_template": "iffail",
                "ei_out": false,
                "invariants": "interval",
                "lib": "ppl",
                "pe_modes": [
                    4
                ],
                "pe_times": 0,
                "scc_depth": 5,
                "simplify_constraints": true,
                "termination": [
                    "qnlrfv1_1_1"
                ],
                "verbosity": 0
            },
            "cputime": 8.859892000000004,
            "date": "2018-09-06T21:45:20.750090",
            "memory": 0,
            "output": "FOUND:\nl4: < < x3 - x4 + 1 > >\nl14: < <  - x4 + x7 - 1 >, <  - x4 + x7 - 1 >, <  - x4 + x6 - 1 > >\nl0: < <  - x4 + x6 > >\nl7: < <  - x4 + x6 - 1 >, < x3 - x5 > >\nl11: < <  - x4 + x7 >, <  - x4 + x7 >, <  - x4 + x6 > >\nl2: < <  - x4 + x6 > >\nl9: < <  - x4 + x6 > >\nl13: < <  - x4 + x7 - 1 >, <  - x4 + x7 - 1 >, <  - x4 + x6 - 1 > >\nl8: < <  - x4 + x6 - 1 >, < x3 - x5 > >\nl15: < <  - x4 + x7 >, <  - x4 + x7 >, <  - x4 + x6 - 1 > >\nl3: < < x3 - x4 > >\nl10: < <  - x4 + x6 > >\nl5: < < x3 - x4 + 1 > >\nl6: < <  - x4 + x6 - 1 >, < x3 - x5 - 1 > >\nl12: < <  - x4 + x7 >, <  - x4 + x7 >, <  - x4 + x6 > >\n",
            "status": "Terminate"
        },
        {
            "config": {
                "different_template": "iffail",
                "ei_out": false,
                "invariants": "interval",
                "lib": "ppl",
                "pe_modes": [
                    4
                ],
                "pe_times": 0,
                "scc_depth": 5,
                "simplify_constraints": true,
                "termination": [
                    "qnlrfv1_2_2"
                ],
                "verbosity": 0
            },
            "cputime": 9.054026999999992,
            "date": "2018-09-06T21:45:36.046710",
            "memory": 264,
            "output": "FOUND:\nl4: < < x3 - x4, x3 - x4 - 1 > >\nl14: < <  - x4 + x6 - 1, 0 > >\nl0: < <  - x4 + x6, 0 > >\nl7: < <  - x4 + x6 - 1, 0 >, < x3 - x5, 0 > >\nl11: < <  - x4 + x6, 0 > >\nl2: < <  - x4 + x6, 0 > >\nl9: < <  - x4 + x6, 0 > >\nl13: < <  - x4 + x6 - 1, 0 > >\nl8: < <  - x4 + x6 - 1, 0 >, < x3 - x5 - 1, x3 - x5 - 1 > >\nl15: < <  - x4 + x6 - 1, 0 > >\nl3: < < x3 - x4, 0 > >\nl10: < <  - x4 + x6, 0 > >\nl5: < < x3 - x4, x3 - x4 - 1 > >\nl6: < <  - x4 + x6 - 1, 0 >, < x3 - x5 - 1, 0 > >\nl12: < <  - x4 + x6 - 1,  - x4 + x6 - 1 > >\n",
            "status": "Terminate"
        },
        {
            "config": {
                "different_template": "iffail",
                "ei_out": false,
                "invariants": "polyhedra",
                "lib": "ppl",
                "pe_modes": [
                    4
                ],
                "pe_times": 0,
                "scc_depth": 5,
                "simplify_constraints": true,
                "termination": [
                    "lrf_pr"
                ],
                "verbosity": 0
            },
            "cputime": 6.495643999999999,
            "date": "2018-09-06T21:45:46.544301",
            "memory": 0,
            "output": "NOT FOUND ",
            "status": "Unknown"
        },
        {
            "config": {
                "different_template": "iffail",
                "ei_out": false,
                "invariants": "polyhedra",
                "lib": "ppl",
                "pe_modes": [
                    4
                ],
                "pe_times": 0,
                "scc_depth": 5,
                "simplify_constraints": true,
                "termination": [
                    "qnlrfv1_1_1"
                ],
                "verbosity": 0
            },
            "cputime": 7.429138000000004,
            "date": "2018-09-06T21:45:58.401063",
            "memory": 0,
            "output": "FOUND:\nl4: < < x3 - x4 > >\nl14: < < x2 - x4 > >\nl0: < < x2 - x4 > >\nl7: < < x2 - x4 >, < x3 - x5 > >\nl11: < < x2 - x4 > >\nl2: < < x2 - x4 > >\nl9: < < x2 - x4 > >\nl13: < < x2 - x4 > >\nl8: < < x2 - x4 >, < x3 - x5 > >\nl15: < < x2 - x4 > >\nl3: < < x3 - x4 > >\nl10: < < x2 - x4 > >\nl5: < < x3 - x4 > >\nl6: < < x2 - x4 >, < x3 - x5 > >\nl12: < < x2 - x4 > >\n",
            "status": "Terminate"
        },
        {
            "config": {
                "different_template": "iffail",
                "ei_out": false,
                "invariants": "polyhedra",
                "lib": "ppl",
                "pe_modes": [
                    4
                ],
                "pe_times": 0,
                "scc_depth": 5,
                "simplify_constraints": true,
                "termination": [
                    "qnlrfv1_2_2"
                ],
                "verbosity": 0
            },
            "cputime": 8.826954000000011,
            "date": "2018-09-06T21:46:12.843889",
            "memory": 0,
            "output": "FOUND:\nl4: < < x3 - x4, 0 > >\nl14: < <  - x4 + x6, 0 > >\nl0: < < x2 - x4, 0 > >\nl7: < <  - x4 + x6, 0 >, < x1 - x5, 0 > >\nl11: < <  - x4 + x6, 0 > >\nl2: < < x2 - x4, 0 > >\nl9: < <  - x4 + x6, 0 > >\nl13: < <  - x4 + x6, 0 > >\nl8: < <  - x4 + x6, 0 >, < x1 - x5, 0 > >\nl15: < <  - x4 + x6, 0 > >\nl3: < < x3 - x4, 0 > >\nl10: < <  - x4 + x6, 0 > >\nl5: < < x3 - x4, 0 > >\nl6: < <  - x4 + x6, 0 >, < x1 - x5, 0 > >\nl12: < <  - x4 + x6, 0 > >\n",
            "status": "Terminate"
        },
        {
            "config": {
                "different_template": "iffail",
                "ei_out": false,
                "invariants": "none",
                "lib": "ppl",
                "pe_modes": [
                    4
                ],
                "pe_times": 1,
                "scc_depth": 5,
                "simplify_constraints": true,
                "termination": [
                    "lrf_pr"
                ],
                "verbosity": 0
            },
            "cputime": 11.286311,
            "date": "2018-09-10T22:31:59.628220",
            "memory": 55072,
            "output": "NOT FOUND ",
            "status": "Unknown"
        },
        {
            "config": {
                "different_template": "iffail",
                "ei_out": false,
                "invariants": "none",
                "lib": "ppl",
                "pe_modes": [
                    4
                ],
                "pe_times": 1,
                "scc_depth": 5,
                "simplify_constraints": true,
                "termination": [
                    "qnlrfv1_1_1"
                ],
                "verbosity": 0
            },
            "cputime": 15.020448,
            "date": "2018-09-10T22:32:30.250028",
            "memory": 3244,
            "output": "FOUND:\nn_l10___15: < <  - x4 + x6 >, <  - x4 + x6 > >\nn_l5___8: < < x3 - x4 > >\nn_l3___7: < < x3 - x4 > >\nn_l7___20: < <  - x4 + x6 >, <  - x4 + x6 > >\nn_l8___14: < <  - x4 + x6 >, <  - x4 + x6 >, < x3 - x5 > >\nn_l9___17: < <  - x4 + x6 >, <  - x4 + x6 > >\nn_l7___16: < <  - x4 + x6 >, <  - x4 + x6 >, < x3 - x5 > >\nn_l2___3: < <  - x4 + x6 > >\nn_l12___23: < <  - x4 >, <  - x4 >, <  - x4 + x6 > >\nn_l15___22: < <  - x4 >, <  - x4 >, <  - x4 + x6 > >\nn_l4___9: < < x3 - x4 > >\nn_l8___18: < <  - x4 + x6 >, <  - x4 + x6 > >\nn_l11___24: < <  - x4 >, <  - x4 >, <  - x4 + x6 > >\nn_l0___2: < <  - x4 + x6 > >\n",
            "status": "Terminate"
        },
        {
            "config": {
                "different_template": "iffail",
                "ei_out": false,
                "invariants": "none",
                "lib": "ppl",
                "pe_modes": [
                    4
                ],
                "pe_times": 1,
                "scc_depth": 5,
                "simplify_constraints": true,
                "termination": [
                    "lrf_pr"
                ],
                "verbosity": 0
            },
            "cputime": 11.087223,
            "date": "2018-09-14T03:14:16.466208",
            "memory": 55780,
            "output": "NOT FOUND ",
            "status": "Unknown"
        },
        {
            "config": {
                "different_template": "iffail",
                "ei_out": false,
                "invariants": "none",
                "lib": "ppl",
                "pe_modes": [
                    4
                ],
                "pe_times": 1,
                "scc_depth": 5,
                "simplify_constraints": true,
                "termination": [
                    "qnlrfv1_1_1"
                ],
                "verbosity": 0
            },
            "cputime": 15.211557,
            "date": "2018-09-14T03:14:47.136398",
            "memory": 2008,
            "output": "FOUND:\nn_l10___14: < <  - x4 + x6 >, <  - x4 + x6 > >\nn_l11___24: < <  - x4 >, <  - x4 >, <  - x4 + x6 > >\nn_l7___20: < <  - x4 + x6 >, <  - x4 + x6 > >\nn_l7___17: < <  - x4 + x6 >, <  - x4 + x6 >, < x3 - x5 > >\nn_l15___22: < <  - x4 >, <  - x4 >, <  - x4 + x6 > >\nn_l2___9: < <  - x4 + x6 > >\nn_l8___18: < <  - x4 + x6 >, <  - x4 + x6 > >\nn_l9___16: < <  - x4 + x6 >, <  - x4 + x6 > >\nn_l0___7: < <  - x4 + x6 > >\nn_l5___3: < < x3 - x4 > >\nn_l4___4: < < x3 - x4 > >\nn_l3___2: < < x3 - x4 > >\nn_l8___15: < <  - x4 + x6 >, <  - x4 + x6 >, < x3 - x5 > >\nn_l12___23: < <  - x4 >, <  - x4 >, <  - x4 + x6 > >\n",
            "status": "Terminate"
        },
        {
            "config": {
                "different_template": "iffail",
                "ei_out": false,
                "invariants": "none",
                "lib": "ppl",
                "pe_modes": [
                    4
                ],
                "pe_times": 1,
                "scc_depth": 5,
                "simplify_constraints": true,
                "termination": [
                    "qnlrfv1_2_2"
                ],
                "verbosity": 0
            },
            "cputime": 19.487539000000005,
            "date": "2018-09-14T03:15:26.666686",
            "memory": 5960,
            "output": "FOUND:\nn_l10___14: < <  - x4 + x6, 0 >, <  - x4 + x6, 0 > >\nn_l11___24: < <  - x4,  - x4 >, <  - x4, 0 >, < x2 - x4, 0 > >\nn_l7___20: < <  - x4 + x6, 0 >, <  - x4 + x6, 0 > >\nn_l7___17: < <  - x4 + x6, 0 >, <  - x4 + x6, 0 >, < x3 - x5, 0 > >\nn_l15___22: < <  - x4,  - x4 >, <  - x4, 0 >, < x2 - x4, 0 > >\nn_l2___9: < <  - x4 + x6, 0 > >\nn_l8___18: < <  - x4 + x6, 0 >, <  - x4 + x6, 0 > >\nn_l9___16: < <  - x4 + x6, 0 >, <  - x4 + x6, 0 > >\nn_l0___7: < <  - x4 + x6, 0 > >\nn_l5___3: < < x3 - x4, 0 > >\nn_l4___4: < < x3 - x4, 0 > >\nn_l3___2: < < x3 - x4, 0 > >\nn_l8___15: < <  - x4 + x6, 0 >, <  - x4 + x6, 0 >, < x3 - x5, 0 > >\nn_l12___23: < <  - x4,  - x4 >, <  - x4, 0 >, < x2 - x4, 0 > >\n",
            "status": "Terminate"
        },
        {
            "config": {
                "different_template": "iffail",
                "ei_out": false,
                "invariants": "interval",
                "lib": "ppl",
                "pe_modes": [
                    4
                ],
                "pe_times": 1,
                "scc_depth": 5,
                "simplify_constraints": true,
                "termination": [
                    "lrf_pr"
                ],
                "verbosity": 0
            },
            "cputime": 11.578925,
            "date": "2018-09-14T03:15:50.250357",
            "memory": 0,
            "output": "NOT FOUND ",
            "status": "Unknown"
        },
        {
            "config": {
                "different_template": "iffail",
                "ei_out": false,
                "invariants": "interval",
                "lib": "ppl",
                "pe_modes": [
                    4
                ],
                "pe_times": 1,
                "scc_depth": 5,
                "simplify_constraints": true,
                "termination": [
                    "qnlrfv1_1_1"
                ],
                "verbosity": 0
            },
            "cputime": 15.569577000000004,
            "date": "2018-09-14T03:16:21.746028",
            "memory": 0,
            "output": "FOUND:\nn_l10___14: < <  - x4 + x6 >, <  - x4 + x6 > >\nn_l11___24: < <  - x4 >, <  - x4 >, <  - x4 + x6 > >\nn_l7___20: < <  - x4 + x6 >, <  - x4 + x6 > >\nn_l7___17: < <  - x4 + x6 >, <  - x4 + x6 >, < x3 - x5 > >\nn_l15___22: < <  - x4 >, <  - x4 >, <  - x4 + x6 > >\nn_l2___9: < <  - x4 + x6 > >\nn_l8___18: < <  - x4 + x6 >, <  - x4 + x6 > >\nn_l9___16: < <  - x4 + x6 >, <  - x4 + x6 > >\nn_l0___7: < <  - x4 + x6 > >\nn_l5___3: < < x3 - x4 > >\nn_l4___4: < < x3 - x4 > >\nn_l3___2: < < x3 - x4 > >\nn_l8___15: < <  - x4 + x6 >, <  - x4 + x6 >, < x3 - x5 > >\nn_l12___23: < <  - x4 >, <  - x4 >, <  - x4 + x6 > >\n",
            "status": "Terminate"
        },
        {
            "config": {
                "different_template": "iffail",
                "ei_out": false,
                "invariants": "interval",
                "lib": "ppl",
                "pe_modes": [
                    4
                ],
                "pe_times": 1,
                "scc_depth": 5,
                "simplify_constraints": true,
                "termination": [
                    "qnlrfv1_2_2"
                ],
                "verbosity": 0
            },
            "cputime": 20.068898999999995,
            "date": "2018-09-14T03:17:02.346229",
            "memory": 0,
            "output": "FOUND:\nn_l10___14: < <  - x4 + x6, 0 >, <  - x4 + x6, 0 > >\nn_l11___24: < <  - x4,  - x4 >, <  - x4, 0 >, < x2 - x4, 0 > >\nn_l7___20: < <  - x4 + x6, 0 >, <  - x4 + x6, 0 > >\nn_l7___17: < <  - x4 + x6, 0 >, <  - x4 + x6, 0 >, < x3 - x5, 0 > >\nn_l15___22: < <  - x4,  - x4 >, <  - x4, 0 >, < x2 - x4, 0 > >\nn_l2___9: < <  - x4 + x6, 0 > >\nn_l8___18: < <  - x4 + x6, 0 >, <  - x4 + x6, 0 > >\nn_l9___16: < <  - x4 + x6, 0 >, <  - x4 + x6, 0 > >\nn_l0___7: < <  - x4 + x6, 0 > >\nn_l5___3: < < x3 - x4, 0 > >\nn_l4___4: < < x3 - x4, 0 > >\nn_l3___2: < < x3 - x4, 0 > >\nn_l8___15: < <  - x4 + x6, 0 >, <  - x4 + x6, 0 >, < x3 - x5, 0 > >\nn_l12___23: < <  - x4,  - x4 >, <  - x4, 0 >, < x2 - x4, 0 > >\n",
            "status": "Terminate"
        },
        {
            "config": {
                "different_template": "iffail",
                "ei_out": false,
                "invariants": "polyhedra",
                "lib": "ppl",
                "pe_modes": [
                    4
                ],
                "pe_times": 1,
                "scc_depth": 5,
                "simplify_constraints": true,
                "termination": [
                    "lrf_pr"
                ],
                "verbosity": 0
            },
            "cputime": 15.319377000000001,
            "date": "2018-09-14T03:17:33.326031",
            "memory": 8244,
            "output": "NOT FOUND ",
            "status": "Unknown"
        },
        {
            "config": {
                "different_template": "iffail",
                "ei_out": false,
                "invariants": "polyhedra",
                "lib": "ppl",
                "pe_modes": [
                    4
                ],
                "pe_times": 1,
                "scc_depth": 5,
                "simplify_constraints": true,
                "termination": [
                    "qnlrfv1_1_1"
                ],
                "verbosity": 0
            },
            "cputime": 16.183664000000004,
            "date": "2018-09-14T03:18:05.946078",
            "memory": 0,
            "output": "FOUND:\nn_l10___14: < < x2 - x4 >, <  - x4 + x6 > >\nn_l7___20: < < x2 - x4 >, <  - x4 + x6 > >\nn_l7___17: < < x2 - x4 >, <  - x4 + x6 >, < x1 - x5 > >\nn_l15___22: < <  - x4 + x6 > >\nn_l8___15: < < x2 - x4 >, <  - x4 + x6 >, < x1 - x5 > >\nn_l2___9: < <  - x4 + x6 > >\nn_l8___18: < < x2 - x4 >, <  - x4 + x6 > >\nn_l9___16: < < x2 - x4 >, <  - x4 + x6 > >\nn_l0___7: < <  - x4 + x6 > >\nn_l5___3: < < x3 - x4 > >\nn_l4___4: < < x3 - x4 > >\nn_l3___2: < < x3 - x4 > >\nn_l11___24: < <  - x4 + x6 > >\nn_l12___23: < <  - x4 + x6 > >\n",
            "status": "Terminate"
        },
        {
            "config": {
                "different_template": "iffail",
                "ei_out": false,
                "invariants": "polyhedra",
                "lib": "ppl",
                "pe_modes": [
                    4
                ],
                "pe_times": 1,
                "scc_depth": 5,
                "simplify_constraints": true,
                "termination": [
                    "qnlrfv1_2_2"
                ],
                "verbosity": 0
            },
            "cputime": 20.322069999999982,
            "date": "2018-09-14T03:18:46.587057",
            "memory": 0,
            "output": "FOUND:\nn_l10___14: < <  - x4 + x6, 0 >, < x2 - x4, 0 > >\nn_l7___20: < <  - x4 + x6, 0 >, < x2 - x4, 0 > >\nn_l7___17: < <  - x4 + x6, 0 >, < x2 - x4, 0 >, < x1 - x5, 0 > >\nn_l15___22: < <  - x4 + x6, 0 > >\nn_l8___15: < <  - x4 + x6, 0 >, < x2 - x4, 0 >, < x1 - x5, 0 > >\nn_l2___9: < <  - x4 + x6, 0 > >\nn_l8___18: < <  - x4 + x6, 0 >, < x2 - x4, 0 > >\nn_l9___16: < <  - x4 + x6, 0 >, < x2 - x4, 0 > >\nn_l0___7: < <  - x4 + x6, 0 > >\nn_l5___3: < < x3 - x4, 0 > >\nn_l4___4: < < x3 - x4, 0 > >\nn_l3___2: < < x3 - x4, 0 > >\nn_l11___24: < <  - x4 + x6, 0 > >\nn_l12___23: < <  - x4 + x6, 0 > >\n",
            "status": "Terminate"
        }
    ],
    "file": "smt2/From_T2/b/bf14.t2.smt2",
    "id": "smt2_From_T2_b_bf14.t2.smt2"
}