{
    "analysis": [
        {
            "config": {
                "different_template": "iffail",
                "ei_out": false,
                "invariants": "none",
                "lib": "ppl",
                "pe_modes": [
                    4
                ],
                "pe_times": 0,
                "scc_depth": 5,
                "simplify_constraints": true,
                "termination": [
                    "lrf_pr"
                ],
                "verbosity": 0
            },
            "cputime": 0.797584,
            "date": "2018-09-06T16:09:28.470238",
            "memory": 44776,
            "output": "FOUND:\nf83_0_main_GE: <  - x1 + 19 >\n",
            "status": "Terminate"
        },
        {
            "config": {
                "different_template": "iffail",
                "ei_out": false,
                "invariants": "none",
                "lib": "ppl",
                "pe_modes": [
                    4
                ],
                "pe_times": 0,
                "scc_depth": 5,
                "simplify_constraints": true,
                "termination": [
                    "qnlrfv1_1_1"
                ],
                "verbosity": 0
            },
            "cputime": 0.8099100000000001,
            "date": "2018-09-06T16:09:30.083014",
            "memory": 16,
            "output": "FOUND:\nf83_0_main_GE: < <  - 4 * x1 + 40 >, <  - x1 + 19 > >\n",
            "status": "Terminate"
        },
        {
            "config": {
                "different_template": "iffail",
                "ei_out": false,
                "invariants": "none",
                "lib": "ppl",
                "pe_modes": [
                    4
                ],
                "pe_times": 0,
                "scc_depth": 5,
                "simplify_constraints": true,
                "termination": [
                    "qnlrfv1_2_2"
                ],
                "verbosity": 0
            },
            "cputime": 0.8129240000000002,
            "date": "2018-09-06T16:09:31.517097",
            "memory": 36,
            "output": "FOUND:\nf83_0_main_GE: < <  - 4 * x1,  - 24 * x1 + 240 >, <  - 2 * x1,  - 21 * x1 + 399 > >\n",
            "status": "Terminate"
        },
        {
            "config": {
                "different_template": "iffail",
                "ei_out": false,
                "invariants": "interval",
                "lib": "ppl",
                "pe_modes": [
                    4
                ],
                "pe_times": 0,
                "scc_depth": 5,
                "simplify_constraints": true,
                "termination": [
                    "lrf_pr"
                ],
                "verbosity": 0
            },
            "cputime": 0.7722089999999997,
            "date": "2018-09-06T16:09:32.981829",
            "memory": 0,
            "output": "FOUND:\nf83_0_main_GE: <  - x1 + 19 >\n",
            "status": "Terminate"
        },
        {
            "config": {
                "different_template": "iffail",
                "ei_out": false,
                "invariants": "interval",
                "lib": "ppl",
                "pe_modes": [
                    4
                ],
                "pe_times": 0,
                "scc_depth": 5,
                "simplify_constraints": true,
                "termination": [
                    "qnlrfv1_1_1"
                ],
                "verbosity": 0
            },
            "cputime": 0.8039059999999997,
            "date": "2018-09-06T16:09:34.446241",
            "memory": 0,
            "output": "FOUND:\nf83_0_main_GE: < <  - 4 * x1 + 40 >, <  - x1 + 19 > >\n",
            "status": "Terminate"
        },
        {
            "config": {
                "different_template": "iffail",
                "ei_out": false,
                "invariants": "interval",
                "lib": "ppl",
                "pe_modes": [
                    4
                ],
                "pe_times": 0,
                "scc_depth": 5,
                "simplify_constraints": true,
                "termination": [
                    "qnlrfv1_2_2"
                ],
                "verbosity": 0
            },
            "cputime": 0.7732599999999998,
            "date": "2018-09-06T16:09:35.692768",
            "memory": 28,
            "output": "FOUND:\nf83_0_main_GE: < <  - 4 * x1,  - 24 * x1 + 240 >, <  - 2 * x1,  - 21 * x1 + 399 > >\n",
            "status": "Terminate"
        },
        {
            "config": {
                "different_template": "iffail",
                "ei_out": false,
                "invariants": "polyhedra",
                "lib": "ppl",
                "pe_modes": [
                    4
                ],
                "pe_times": 0,
                "scc_depth": 5,
                "simplify_constraints": true,
                "termination": [
                    "lrf_pr"
                ],
                "verbosity": 0
            },
            "cputime": 0.8163060000000003,
            "date": "2018-09-06T16:09:37.298001",
            "memory": 112,
            "output": "FOUND:\nf83_0_main_GE: <  - x1 + 19 >\n",
            "status": "Terminate"
        },
        {
            "config": {
                "different_template": "iffail",
                "ei_out": false,
                "invariants": "polyhedra",
                "lib": "ppl",
                "pe_modes": [
                    4
                ],
                "pe_times": 0,
                "scc_depth": 5,
                "simplify_constraints": true,
                "termination": [
                    "qnlrfv1_1_1"
                ],
                "verbosity": 0
            },
            "cputime": 0.8146339999999999,
            "date": "2018-09-06T16:09:38.814085",
            "memory": 0,
            "output": "FOUND:\nf83_0_main_GE: < <  - 4 * x1 + 40 >, <  - x1 + 19 > >\n",
            "status": "Terminate"
        },
        {
            "config": {
                "different_template": "iffail",
                "ei_out": false,
                "invariants": "polyhedra",
                "lib": "ppl",
                "pe_modes": [
                    4
                ],
                "pe_times": 0,
                "scc_depth": 5,
                "simplify_constraints": true,
                "termination": [
                    "qnlrfv1_2_2"
                ],
                "verbosity": 0
            },
            "cputime": 0.8181920000000003,
            "date": "2018-09-06T16:09:40.234063",
            "memory": 0,
            "output": "FOUND:\nf83_0_main_GE: < <  - x1,  - 6 * x1 + 60 >, <  - 2 * x1,  - 21 * x1 + 399 > >\n",
            "status": "Terminate"
        },
        {
            "config": {
                "different_template": "iffail",
                "ei_out": false,
                "invariants": "none",
                "lib": "ppl",
                "pe_modes": [
                    4
                ],
                "pe_times": 1,
                "scc_depth": 5,
                "simplify_constraints": true,
                "termination": [
                    "lrf_pr"
                ],
                "verbosity": 0
            },
            "cputime": 1.740436,
            "date": "2018-09-10T18:51:42.978899",
            "memory": 45948,
            "output": "FOUND:\nn_f83_0_main_GE___1: <  - x1 + 19 >\nn_f83_0_main_GE___3: <  - x1 + 10 >\n",
            "status": "Terminate"
        }
    ],
    "file": "smt2/From_AProVE_2014/e/Exc.jar-obl-8.smt2",
    "id": "smt2_From_AProVE_2014_e_Exc.jar-obl-8.smt2"
}