{
    "analysis": [
        {
            "config": {
                "different_template": "iffail",
                "ei_out": false,
                "invariants": "none",
                "lib": "ppl",
                "pe_modes": [
                    4
                ],
                "pe_times": 0,
                "scc_depth": 5,
                "simplify_constraints": true,
                "termination": [
                    "lrf_pr"
                ],
                "verbosity": 0
            },
            "cputime": 1.321014,
            "date": "2018-09-06T14:41:27.713260",
            "memory": 45704,
            "output": "FOUND:\nf167_0_log_LT': < 4 * x2 - 3 * x3 - 2 >\nf167_0_log_LT: <  - 3 * x1 + 4 * x2 >\n",
            "status": "Terminate"
        },
        {
            "config": {
                "different_template": "iffail",
                "ei_out": false,
                "invariants": "none",
                "lib": "ppl",
                "pe_modes": [
                    4
                ],
                "pe_times": 0,
                "scc_depth": 5,
                "simplify_constraints": true,
                "termination": [
                    "qnlrfv1_1_1"
                ],
                "verbosity": 0
            },
            "cputime": 1.286677,
            "date": "2018-09-06T14:41:30.602045",
            "memory": 20,
            "output": "FOUND:\nf167_0_log_LT': < <  - x1 + x2 > >\nf167_0_log_LT: < <  - x1 + x2 > >\n",
            "status": "Terminate"
        },
        {
            "config": {
                "different_template": "iffail",
                "ei_out": false,
                "invariants": "none",
                "lib": "ppl",
                "pe_modes": [
                    4
                ],
                "pe_times": 0,
                "scc_depth": 5,
                "simplify_constraints": true,
                "termination": [
                    "qnlrfv1_2_2"
                ],
                "verbosity": 0
            },
            "cputime": 1.296338,
            "date": "2018-09-06T14:41:33.370168",
            "memory": 32,
            "output": "FOUND:\nf167_0_log_LT': < <  - x1 + x2,  - x1 + x2 > >\nf167_0_log_LT: < <  - x1 + x2,  - x1 + x2 > >\n",
            "status": "Terminate"
        },
        {
            "config": {
                "different_template": "iffail",
                "ei_out": false,
                "invariants": "interval",
                "lib": "ppl",
                "pe_modes": [
                    4
                ],
                "pe_times": 0,
                "scc_depth": 5,
                "simplify_constraints": true,
                "termination": [
                    "lrf_pr"
                ],
                "verbosity": 0
            },
            "cputime": 1.292205,
            "date": "2018-09-06T14:41:35.985984",
            "memory": 0,
            "output": "FOUND:\nf167_0_log_LT': < 4 * x2 - 3 * x3 - 2 >\nf167_0_log_LT: <  - 3 * x1 + 4 * x2 >\n",
            "status": "Terminate"
        },
        {
            "config": {
                "different_template": "iffail",
                "ei_out": false,
                "invariants": "interval",
                "lib": "ppl",
                "pe_modes": [
                    4
                ],
                "pe_times": 0,
                "scc_depth": 5,
                "simplify_constraints": true,
                "termination": [
                    "qnlrfv1_1_1"
                ],
                "verbosity": 0
            },
            "cputime": 1.3361630000000002,
            "date": "2018-09-06T14:41:38.942700",
            "memory": 0,
            "output": "FOUND:\nf167_0_log_LT': < <  - x1 + x2 > >\nf167_0_log_LT: < <  - x1 + x2 > >\n",
            "status": "Terminate"
        },
        {
            "config": {
                "different_template": "iffail",
                "ei_out": false,
                "invariants": "interval",
                "lib": "ppl",
                "pe_modes": [
                    4
                ],
                "pe_times": 0,
                "scc_depth": 5,
                "simplify_constraints": true,
                "termination": [
                    "qnlrfv1_2_2"
                ],
                "verbosity": 0
            },
            "cputime": 1.3026960000000005,
            "date": "2018-09-06T14:41:41.767958",
            "memory": 0,
            "output": "FOUND:\nf167_0_log_LT': < <  - x1 + x2,  - x1 + x2 > >\nf167_0_log_LT: < <  - x1 + x2,  - x1 + x2 > >\n",
            "status": "Terminate"
        },
        {
            "config": {
                "different_template": "iffail",
                "ei_out": false,
                "invariants": "polyhedra",
                "lib": "ppl",
                "pe_modes": [
                    4
                ],
                "pe_times": 0,
                "scc_depth": 5,
                "simplify_constraints": true,
                "termination": [
                    "lrf_pr"
                ],
                "verbosity": 0
            },
            "cputime": 1.293851,
            "date": "2018-09-06T14:41:44.314018",
            "memory": 32,
            "output": "FOUND:\nf167_0_log_LT': < 4 * x2 - 3 * x3 - 2 >\nf167_0_log_LT: <  - 3 * x1 + 4 * x2 >\n",
            "status": "Terminate"
        },
        {
            "config": {
                "different_template": "iffail",
                "ei_out": false,
                "invariants": "polyhedra",
                "lib": "ppl",
                "pe_modes": [
                    4
                ],
                "pe_times": 0,
                "scc_depth": 5,
                "simplify_constraints": true,
                "termination": [
                    "qnlrfv1_1_1"
                ],
                "verbosity": 0
            },
            "cputime": 1.3341190000000007,
            "date": "2018-09-06T14:41:47.181596",
            "memory": 36,
            "output": "FOUND:\nf167_0_log_LT': < <  - x1 + x2 > >\nf167_0_log_LT: < <  - x1 + x2 > >\n",
            "status": "Terminate"
        },
        {
            "config": {
                "different_template": "iffail",
                "ei_out": false,
                "invariants": "polyhedra",
                "lib": "ppl",
                "pe_modes": [
                    4
                ],
                "pe_times": 0,
                "scc_depth": 5,
                "simplify_constraints": true,
                "termination": [
                    "qnlrfv1_2_2"
                ],
                "verbosity": 0
            },
            "cputime": 1.3376550000000003,
            "date": "2018-09-06T14:41:50.070683",
            "memory": 0,
            "output": "FOUND:\nf167_0_log_LT': < <  - x1 + x2,  - x1 + x2 > >\nf167_0_log_LT: < <  - x1 + x2,  - x1 + x2 > >\n",
            "status": "Terminate"
        },
        {
            "config": {
                "different_template": "iffail",
                "ei_out": false,
                "invariants": "none",
                "lib": "ppl",
                "pe_modes": [
                    4
                ],
                "pe_times": 1,
                "scc_depth": 5,
                "simplify_constraints": true,
                "termination": [
                    "lrf_pr"
                ],
                "verbosity": 0
            },
            "cputime": 2.678064,
            "date": "2018-09-10T16:37:09.499748",
            "memory": 47124,
            "output": "FOUND:\nn_f167_0_log_LT___1: <  - x1 + x2 >\n",
            "status": "Terminate"
        },
        {
            "config": {
                "different_template": "iffail",
                "ei_out": false,
                "invariants": "none",
                "lib": "ppl",
                "pe_modes": [
                    4
                ],
                "pe_times": 1,
                "scc_depth": 5,
                "simplify_constraints": true,
                "termination": [
                    "lrf_pr"
                ],
                "verbosity": 0
            },
            "cputime": 2.772844,
            "date": "2018-09-13T19:15:21.166739",
            "memory": 46912,
            "output": "FOUND:\nn_f167_0_log_LT___2: <  - x1 + x2 >\n",
            "status": "Terminate"
        },
        {
            "config": {
                "different_template": "iffail",
                "ei_out": false,
                "invariants": "none",
                "lib": "ppl",
                "pe_modes": [
                    4
                ],
                "pe_times": 1,
                "scc_depth": 5,
                "simplify_constraints": true,
                "termination": [
                    "qnlrfv1_1_1"
                ],
                "verbosity": 0
            },
            "cputime": 2.737813,
            "date": "2018-09-13T19:15:26.874790",
            "memory": 4,
            "output": "FOUND:\nn_f167_0_log_LT___2: < <  - x1 + x2 > >\n",
            "status": "Terminate"
        },
        {
            "config": {
                "different_template": "iffail",
                "ei_out": false,
                "invariants": "none",
                "lib": "ppl",
                "pe_modes": [
                    4
                ],
                "pe_times": 1,
                "scc_depth": 5,
                "simplify_constraints": true,
                "termination": [
                    "qnlrfv1_2_2"
                ],
                "verbosity": 0
            },
            "cputime": 2.7777290000000012,
            "date": "2018-09-13T19:15:32.824520",
            "memory": 0,
            "output": "FOUND:\nn_f167_0_log_LT___2: < < x2 - x3,  - 2 * x1 + x2 + x3 > >\n",
            "status": "Terminate"
        },
        {
            "config": {
                "different_template": "iffail",
                "ei_out": false,
                "invariants": "interval",
                "lib": "ppl",
                "pe_modes": [
                    4
                ],
                "pe_times": 1,
                "scc_depth": 5,
                "simplify_constraints": true,
                "termination": [
                    "lrf_pr"
                ],
                "verbosity": 0
            },
            "cputime": 2.7805920000000013,
            "date": "2018-09-13T19:15:38.554793",
            "memory": 8,
            "output": "FOUND:\nn_f167_0_log_LT___2: <  - x1 + x2 >\n",
            "status": "Terminate"
        },
        {
            "config": {
                "different_template": "iffail",
                "ei_out": false,
                "invariants": "interval",
                "lib": "ppl",
                "pe_modes": [
                    4
                ],
                "pe_times": 1,
                "scc_depth": 5,
                "simplify_constraints": true,
                "termination": [
                    "qnlrfv1_1_1"
                ],
                "verbosity": 0
            },
            "cputime": 2.877774,
            "date": "2018-09-13T19:15:44.437960",
            "memory": 4,
            "output": "FOUND:\nn_f167_0_log_LT___2: < <  - x1 + x2 > >\n",
            "status": "Terminate"
        },
        {
            "config": {
                "different_template": "iffail",
                "ei_out": false,
                "invariants": "interval",
                "lib": "ppl",
                "pe_modes": [
                    4
                ],
                "pe_times": 1,
                "scc_depth": 5,
                "simplify_constraints": true,
                "termination": [
                    "qnlrfv1_2_2"
                ],
                "verbosity": 0
            },
            "cputime": 2.8760709999999974,
            "date": "2018-09-13T19:15:50.457491",
            "memory": 0,
            "output": "FOUND:\nn_f167_0_log_LT___2: < <  - x1 + x2,  - x1 + x2 > >\n",
            "status": "Terminate"
        },
        {
            "config": {
                "different_template": "iffail",
                "ei_out": false,
                "invariants": "polyhedra",
                "lib": "ppl",
                "pe_modes": [
                    4
                ],
                "pe_times": 1,
                "scc_depth": 5,
                "simplify_constraints": true,
                "termination": [
                    "lrf_pr"
                ],
                "verbosity": 0
            },
            "cputime": 2.6990909999999984,
            "date": "2018-09-13T19:15:55.993350",
            "memory": 200,
            "output": "FOUND:\nn_f167_0_log_LT___2: <  - x1 + x2 >\n",
            "status": "Terminate"
        },
        {
            "config": {
                "different_template": "iffail",
                "ei_out": false,
                "invariants": "polyhedra",
                "lib": "ppl",
                "pe_modes": [
                    4
                ],
                "pe_times": 1,
                "scc_depth": 5,
                "simplify_constraints": true,
                "termination": [
                    "qnlrfv1_1_1"
                ],
                "verbosity": 0
            },
            "cputime": 2.802548000000002,
            "date": "2018-09-13T19:16:01.870530",
            "memory": 0,
            "output": "FOUND:\nn_f167_0_log_LT___2: < <  - x1 + x2 > >\n",
            "status": "Terminate"
        },
        {
            "config": {
                "different_template": "iffail",
                "ei_out": false,
                "invariants": "polyhedra",
                "lib": "ppl",
                "pe_modes": [
                    4
                ],
                "pe_times": 1,
                "scc_depth": 5,
                "simplify_constraints": true,
                "termination": [
                    "qnlrfv1_2_2"
                ],
                "verbosity": 0
            },
            "cputime": 2.8106189999999995,
            "date": "2018-09-13T19:16:07.676686",
            "memory": 0,
            "output": "FOUND:\nn_f167_0_log_LT___2: < < x2 - x3,  - 2 * x1 + x2 + x3 > >\n",
            "status": "Terminate"
        }
    ],
    "file": "smt2/From_AProVE_2014/l/LogRecursive.jar-obl-8.smt2",
    "id": "smt2_From_AProVE_2014_l_LogRecursive.jar-obl-8.smt2"
}