{
    "analysis": [
        {
            "config": {
                "different_template": "iffail",
                "ei_out": false,
                "invariants": "none",
                "lib": "ppl",
                "pe_modes": [
                    4
                ],
                "pe_times": 0,
                "scc_depth": 5,
                "simplify_constraints": true,
                "termination": [
                    "lrf_pr"
                ],
                "verbosity": 0
            },
            "cputime": 44.831903000000004,
            "date": "2018-09-07T11:43:55.948451",
            "memory": 158472,
            "output": "NOT FOUND ",
            "status": "Unknown"
        },
        {
            "config": {
                "different_template": "iffail",
                "ei_out": false,
                "invariants": "none",
                "lib": "ppl",
                "pe_modes": [
                    4
                ],
                "pe_times": 0,
                "scc_depth": 5,
                "simplify_constraints": true,
                "termination": [
                    "qnlrfv1_1_1"
                ],
                "verbosity": 0
            },
            "cputime": 140.408392,
            "date": "2018-09-07T11:47:52.174800",
            "memory": 0,
            "output": "NOT FOUND ",
            "status": "Unknown"
        },
        {
            "config": {
                "different_template": "iffail",
                "ei_out": false,
                "invariants": "none",
                "lib": "ppl",
                "pe_modes": [
                    4
                ],
                "pe_times": 0,
                "scc_depth": 5,
                "simplify_constraints": true,
                "termination": [
                    "qnlrfv1_2_2"
                ],
                "verbosity": 0
            },
            "cputime": 290.673405,
            "date": "2018-09-07T11:55:57.237486",
            "memory": 42076,
            "output": "NOT FOUND ",
            "status": "Unknown"
        },
        {
            "config": {
                "different_template": "iffail",
                "ei_out": false,
                "invariants": "interval",
                "lib": "ppl",
                "pe_modes": [
                    4
                ],
                "pe_times": 0,
                "scc_depth": 5,
                "simplify_constraints": true,
                "termination": [
                    "lrf_pr"
                ],
                "verbosity": 0
            },
            "cputime": 47.84735700000005,
            "date": "2018-09-07T11:57:15.481955",
            "memory": 0,
            "output": "NOT FOUND ",
            "status": "Unknown"
        },
        {
            "config": {
                "different_template": "iffail",
                "ei_out": false,
                "invariants": "interval",
                "lib": "ppl",
                "pe_modes": [
                    4
                ],
                "pe_times": 0,
                "scc_depth": 5,
                "simplify_constraints": true,
                "termination": [
                    "qnlrfv1_1_1"
                ],
                "verbosity": 0
            },
            "cputime": 141.34536300000002,
            "date": "2018-09-07T12:01:12.370368",
            "memory": 0,
            "output": "NOT FOUND ",
            "status": "Unknown"
        },
        {
            "config": {
                "different_template": "iffail",
                "ei_out": false,
                "invariants": "interval",
                "lib": "ppl",
                "pe_modes": [
                    4
                ],
                "pe_times": 0,
                "scc_depth": 5,
                "simplify_constraints": true,
                "termination": [
                    "qnlrfv1_2_2"
                ],
                "verbosity": 0
            },
            "cputime": 297.896818,
            "date": "2018-09-07T12:09:56.576000",
            "memory": 0,
            "output": "TL",
            "status": "Time Limit"
        },
        {
            "config": {
                "different_template": "iffail",
                "ei_out": false,
                "invariants": "polyhedra",
                "lib": "ppl",
                "pe_modes": [
                    4
                ],
                "pe_times": 0,
                "scc_depth": 5,
                "simplify_constraints": true,
                "termination": [
                    "lrf_pr"
                ],
                "verbosity": 0
            },
            "cputime": 53.47915,
            "date": "2018-09-07T12:11:35.394618",
            "memory": 0,
            "output": "NOT FOUND ",
            "status": "Unknown"
        },
        {
            "config": {
                "different_template": "iffail",
                "ei_out": false,
                "invariants": "polyhedra",
                "lib": "ppl",
                "pe_modes": [
                    4
                ],
                "pe_times": 0,
                "scc_depth": 5,
                "simplify_constraints": true,
                "termination": [
                    "qnlrfv1_1_1"
                ],
                "verbosity": 0
            },
            "cputime": 163.79632799999996,
            "date": "2018-09-07T12:15:52.258145",
            "memory": 0,
            "output": "NOT FOUND ",
            "status": "Unknown"
        },
        {
            "config": {
                "different_template": "iffail",
                "ei_out": false,
                "invariants": "polyhedra",
                "lib": "ppl",
                "pe_modes": [
                    4
                ],
                "pe_times": 0,
                "scc_depth": 5,
                "simplify_constraints": true,
                "termination": [
                    "qnlrfv1_2_2"
                ],
                "verbosity": 0
            },
            "cputime": 299.8162590000001,
            "date": "2018-09-07T12:21:32.254121",
            "memory": 8196,
            "output": "TL",
            "status": "Time Limit"
        },
        {
            "config": {
                "different_template": "iffail",
                "ei_out": false,
                "invariants": "none",
                "lib": "ppl",
                "pe_modes": [
                    4
                ],
                "pe_times": 1,
                "scc_depth": 5,
                "simplify_constraints": true,
                "termination": [
                    "lrf_pr"
                ],
                "verbosity": 0
            },
            "cputime": 111.484388,
            "date": "2018-09-11T20:11:55.646335",
            "memory": 203292,
            "output": "NOT FOUND ",
            "status": "Unknown"
        },
        {
            "config": {
                "different_template": "iffail",
                "ei_out": false,
                "invariants": "none",
                "lib": "ppl",
                "pe_modes": [
                    4
                ],
                "pe_times": 1,
                "scc_depth": 5,
                "simplify_constraints": true,
                "termination": [
                    "qnlrfv1_1_1"
                ],
                "verbosity": 0
            },
            "cputime": 305.99336900000003,
            "date": "2018-09-11T20:22:11.388609",
            "memory": 0,
            "output": "TL",
            "status": "Time Limit"
        },
        {
            "config": {
                "different_template": "iffail",
                "ei_out": false,
                "invariants": "none",
                "lib": "ppl",
                "pe_modes": [
                    4
                ],
                "pe_times": 1,
                "scc_depth": 5,
                "simplify_constraints": true,
                "termination": [
                    "qnlrfv1_2_2"
                ],
                "verbosity": 0
            },
            "cputime": 305.811288,
            "date": "2018-09-11T20:32:27.697631",
            "memory": 0,
            "output": "TL",
            "status": "Time Limit"
        },
        {
            "config": {
                "different_template": "iffail",
                "ei_out": false,
                "invariants": "interval",
                "lib": "ppl",
                "pe_modes": [
                    4
                ],
                "pe_times": 1,
                "scc_depth": 5,
                "simplify_constraints": true,
                "termination": [
                    "lrf_pr"
                ],
                "verbosity": 0
            },
            "cputime": 110.27882099999995,
            "date": "2018-09-11T20:36:10.318479",
            "memory": 0,
            "output": "NOT FOUND ",
            "status": "Unknown"
        },
        {
            "config": {
                "different_template": "iffail",
                "ei_out": false,
                "invariants": "interval",
                "lib": "ppl",
                "pe_modes": [
                    4
                ],
                "pe_times": 1,
                "scc_depth": 5,
                "simplify_constraints": true,
                "termination": [
                    "qnlrfv1_1_1"
                ],
                "verbosity": 0
            },
            "cputime": 305.781075,
            "date": "2018-09-11T20:46:27.793752",
            "memory": 0,
            "output": "TL",
            "status": "Time Limit"
        },
        {
            "config": {
                "different_template": "iffail",
                "ei_out": false,
                "invariants": "interval",
                "lib": "ppl",
                "pe_modes": [
                    4
                ],
                "pe_times": 1,
                "scc_depth": 5,
                "simplify_constraints": true,
                "termination": [
                    "qnlrfv1_2_2"
                ],
                "verbosity": 0
            },
            "cputime": 305.9490799999998,
            "date": "2018-09-11T20:56:45.273136",
            "memory": 0,
            "output": "TL",
            "status": "Time Limit"
        },
        {
            "config": {
                "different_template": "iffail",
                "ei_out": false,
                "invariants": "polyhedra",
                "lib": "ppl",
                "pe_modes": [
                    4
                ],
                "pe_times": 1,
                "scc_depth": 5,
                "simplify_constraints": true,
                "termination": [
                    "lrf_pr"
                ],
                "verbosity": 0
            },
            "cputime": 110.2829570000001,
            "date": "2018-09-11T21:00:28.686704",
            "memory": 96,
            "output": "NOT FOUND ",
            "status": "Unknown"
        },
        {
            "config": {
                "different_template": "iffail",
                "ei_out": false,
                "invariants": "polyhedra",
                "lib": "ppl",
                "pe_modes": [
                    4
                ],
                "pe_times": 1,
                "scc_depth": 5,
                "simplify_constraints": true,
                "termination": [
                    "qnlrfv1_1_1"
                ],
                "verbosity": 0
            },
            "cputime": 305.63038199999994,
            "date": "2018-09-11T21:10:43.984267",
            "memory": 0,
            "output": "TL",
            "status": "Time Limit"
        },
        {
            "config": {
                "different_template": "iffail",
                "ei_out": false,
                "invariants": "polyhedra",
                "lib": "ppl",
                "pe_modes": [
                    4
                ],
                "pe_times": 1,
                "scc_depth": 5,
                "simplify_constraints": true,
                "termination": [
                    "qnlrfv1_2_2"
                ],
                "verbosity": 0
            },
            "cputime": 305.8381800000002,
            "date": "2018-09-11T21:21:01.533810",
            "memory": 0,
            "output": "TL",
            "status": "Time Limit"
        },
        {
            "config": {
                "different_template": "never",
                "ei_out": false,
                "invariants": "none",
                "lib": "ppl",
                "pe_modes": [
                    4
                ],
                "pe_times": 1,
                "scc_depth": 5,
                "simplify_constraints": true,
                "termination": [
                    "lrf_pr"
                ],
                "verbosity": 0
            },
            "cputime": 70.079039,
            "date": "2018-09-15T18:25:24.230162",
            "memory": 163352,
            "output": "NOT FOUND ",
            "status": "Unknown"
        },
        {
            "config": {
                "different_template": "iffail",
                "ei_out": false,
                "invariants": "none",
                "lib": "ppl",
                "pe_modes": [
                    4
                ],
                "pe_times": 1,
                "scc_depth": 5,
                "simplify_constraints": true,
                "termination": [
                    "lrf_pr"
                ],
                "verbosity": 0
            },
            "cputime": 108.527277,
            "date": "2018-09-15T18:29:02.622312",
            "memory": 39000,
            "output": "NOT FOUND ",
            "status": "Unknown"
        },
        {
            "config": {
                "different_template": "always",
                "ei_out": false,
                "invariants": "none",
                "lib": "ppl",
                "pe_modes": [
                    4
                ],
                "pe_times": 1,
                "scc_depth": 5,
                "simplify_constraints": true,
                "termination": [
                    "lrf_pr"
                ],
                "verbosity": 0
            },
            "cputime": 73.22252,
            "date": "2018-09-15T18:31:30.993808",
            "memory": 60,
            "output": "NOT FOUND ",
            "status": "Unknown"
        },
        {
            "config": {
                "different_template": "never",
                "ei_out": false,
                "invariants": "none",
                "lib": "ppl",
                "pe_modes": [
                    4
                ],
                "pe_times": 1,
                "scc_depth": 5,
                "simplify_constraints": true,
                "termination": [
                    "qnlrfv1_1_1"
                ],
                "verbosity": 0
            },
            "cputime": 211.11529999999996,
            "date": "2018-09-15T18:38:36.574721",
            "memory": 0,
            "output": "NOT FOUND ",
            "status": "Unknown"
        },
        {
            "config": {
                "different_template": "iffail",
                "ei_out": false,
                "invariants": "none",
                "lib": "ppl",
                "pe_modes": [
                    4
                ],
                "pe_times": 1,
                "scc_depth": 5,
                "simplify_constraints": true,
                "termination": [
                    "qnlrfv1_1_1"
                ],
                "verbosity": 0
            },
            "cputime": 305.63292,
            "date": "2018-09-15T18:48:50.335802",
            "memory": 0,
            "output": "TL",
            "status": "Time Limit"
        },
        {
            "config": {
                "different_template": "always",
                "ei_out": false,
                "invariants": "none",
                "lib": "ppl",
                "pe_modes": [
                    4
                ],
                "pe_times": 1,
                "scc_depth": 5,
                "simplify_constraints": true,
                "termination": [
                    "qnlrfv1_1_1"
                ],
                "verbosity": 0
            },
            "cputime": 224.74952500000003,
            "date": "2018-09-15T18:56:22.174324",
            "memory": 0,
            "output": "NOT FOUND ",
            "status": "Unknown"
        },
        {
            "config": {
                "different_template": "never",
                "ei_out": false,
                "invariants": "none",
                "lib": "ppl",
                "pe_modes": [
                    4
                ],
                "pe_times": 1,
                "scc_depth": 5,
                "simplify_constraints": true,
                "termination": [
                    "qnlrfv1_2_2"
                ],
                "verbosity": 0
            },
            "cputime": 305.5482989999999,
            "date": "2018-09-15T19:06:36.875412",
            "memory": 0,
            "output": "TL",
            "status": "Time Limit"
        },
        {
            "config": {
                "different_template": "iffail",
                "ei_out": false,
                "invariants": "none",
                "lib": "ppl",
                "pe_modes": [
                    4
                ],
                "pe_times": 1,
                "scc_depth": 5,
                "simplify_constraints": true,
                "termination": [
                    "qnlrfv1_2_2"
                ],
                "verbosity": 0
            },
            "cputime": 305.888888,
            "date": "2018-09-15T19:16:51.196406",
            "memory": 0,
            "output": "TL",
            "status": "Time Limit"
        },
        {
            "config": {
                "different_template": "always",
                "ei_out": false,
                "invariants": "none",
                "lib": "ppl",
                "pe_modes": [
                    4
                ],
                "pe_times": 1,
                "scc_depth": 5,
                "simplify_constraints": true,
                "termination": [
                    "qnlrfv1_2_2"
                ],
                "verbosity": 0
            },
            "cputime": 305.6805309999999,
            "date": "2018-09-15T19:27:03.759965",
            "memory": 87644,
            "output": "TL",
            "status": "Time Limit"
        },
        {
            "config": {
                "different_template": "never",
                "ei_out": false,
                "invariants": "none",
                "lib": "ppl",
                "pe_modes": [
                    4
                ],
                "pe_times": 1,
                "scc_depth": 5,
                "simplify_constraints": true,
                "termination": [
                    "lrf_pr"
                ],
                "verbosity": 0
            },
            "cputime": 71.15607199999984,
            "date": "2018-09-15T19:29:26.837991",
            "memory": 0,
            "output": "NOT FOUND ",
            "status": "Unknown"
        },
        {
            "config": {
                "different_template": "iffail",
                "ei_out": false,
                "invariants": "none",
                "lib": "ppl",
                "pe_modes": [
                    4
                ],
                "pe_times": 1,
                "scc_depth": 5,
                "simplify_constraints": true,
                "termination": [
                    "lrf_pr"
                ],
                "verbosity": 0
            },
            "cputime": 109.59553800000009,
            "date": "2018-09-15T19:33:07.344326",
            "memory": 0,
            "output": "NOT FOUND ",
            "status": "Unknown"
        },
        {
            "config": {
                "different_template": "always",
                "ei_out": false,
                "invariants": "none",
                "lib": "ppl",
                "pe_modes": [
                    4
                ],
                "pe_times": 1,
                "scc_depth": 5,
                "simplify_constraints": true,
                "termination": [
                    "lrf_pr"
                ],
                "verbosity": 0
            },
            "cputime": 72.50861599999982,
            "date": "2018-09-15T19:35:32.390776",
            "memory": 0,
            "output": "NOT FOUND ",
            "status": "Unknown"
        },
        {
            "config": {
                "different_template": "never",
                "ei_out": false,
                "invariants": "none",
                "lib": "ppl",
                "pe_modes": [
                    4
                ],
                "pe_times": 1,
                "scc_depth": 5,
                "simplify_constraints": true,
                "termination": [
                    "qnlrfv1_1_1"
                ],
                "verbosity": 0
            },
            "cputime": 212.808981,
            "date": "2018-09-15T19:42:39.476859",
            "memory": 0,
            "output": "NOT FOUND ",
            "status": "Unknown"
        },
        {
            "config": {
                "different_template": "iffail",
                "ei_out": false,
                "invariants": "none",
                "lib": "ppl",
                "pe_modes": [
                    4
                ],
                "pe_times": 1,
                "scc_depth": 5,
                "simplify_constraints": true,
                "termination": [
                    "qnlrfv1_1_1"
                ],
                "verbosity": 0
            },
            "cputime": 305.5089200000002,
            "date": "2018-09-15T19:52:53.682598",
            "memory": 0,
            "output": "TL",
            "status": "Time Limit"
        },
        {
            "config": {
                "different_template": "always",
                "ei_out": false,
                "invariants": "none",
                "lib": "ppl",
                "pe_modes": [
                    4
                ],
                "pe_times": 1,
                "scc_depth": 5,
                "simplify_constraints": true,
                "termination": [
                    "qnlrfv1_1_1"
                ],
                "verbosity": 0
            },
            "cputime": 226.7450459999995,
            "date": "2018-09-15T20:00:29.254883",
            "memory": 0,
            "output": "NOT FOUND ",
            "status": "Unknown"
        },
        {
            "config": {
                "different_template": "never",
                "ei_out": false,
                "invariants": "none",
                "lib": "ppl",
                "pe_modes": [
                    4
                ],
                "pe_times": 1,
                "scc_depth": 5,
                "simplify_constraints": true,
                "termination": [
                    "qnlrfv1_2_2"
                ],
                "verbosity": 0
            },
            "cputime": 305.7679819999996,
            "date": "2018-09-15T20:10:42.984799",
            "memory": 0,
            "output": "TL",
            "status": "Time Limit"
        },
        {
            "config": {
                "different_template": "iffail",
                "ei_out": false,
                "invariants": "none",
                "lib": "ppl",
                "pe_modes": [
                    4
                ],
                "pe_times": 1,
                "scc_depth": 5,
                "simplify_constraints": true,
                "termination": [
                    "qnlrfv1_2_2"
                ],
                "verbosity": 0
            },
            "cputime": 305.21984800000024,
            "date": "2018-09-15T20:20:55.854613",
            "memory": 0,
            "output": "TL",
            "status": "Time Limit"
        },
        {
            "config": {
                "different_template": "always",
                "ei_out": false,
                "invariants": "none",
                "lib": "ppl",
                "pe_modes": [
                    4
                ],
                "pe_times": 1,
                "scc_depth": 5,
                "simplify_constraints": true,
                "termination": [
                    "qnlrfv1_2_2"
                ],
                "verbosity": 0
            },
            "cputime": 305.31010200000037,
            "date": "2018-09-15T20:31:08.559965",
            "memory": 12,
            "output": "TL",
            "status": "Time Limit"
        },
        {
            "config": {
                "different_template": "never",
                "ei_out": false,
                "invariants": "interval",
                "lib": "ppl",
                "pe_modes": [
                    4
                ],
                "pe_times": 1,
                "scc_depth": 5,
                "simplify_constraints": true,
                "termination": [
                    "lrf_pr"
                ],
                "verbosity": 0
            },
            "cputime": 70.19535100000044,
            "date": "2018-09-15T20:33:29.398806",
            "memory": 0,
            "output": "NOT FOUND ",
            "status": "Unknown"
        },
        {
            "config": {
                "different_template": "iffail",
                "ei_out": false,
                "invariants": "interval",
                "lib": "ppl",
                "pe_modes": [
                    4
                ],
                "pe_times": 1,
                "scc_depth": 5,
                "simplify_constraints": true,
                "termination": [
                    "lrf_pr"
                ],
                "verbosity": 0
            },
            "cputime": 108.82088599999976,
            "date": "2018-09-15T20:37:08.166538",
            "memory": 0,
            "output": "NOT FOUND ",
            "status": "Unknown"
        },
        {
            "config": {
                "different_template": "always",
                "ei_out": false,
                "invariants": "interval",
                "lib": "ppl",
                "pe_modes": [
                    4
                ],
                "pe_times": 1,
                "scc_depth": 5,
                "simplify_constraints": true,
                "termination": [
                    "lrf_pr"
                ],
                "verbosity": 0
            },
            "cputime": 74.69759899999991,
            "date": "2018-09-15T20:39:38.358742",
            "memory": 0,
            "output": "NOT FOUND ",
            "status": "Unknown"
        },
        {
            "config": {
                "different_template": "never",
                "ei_out": false,
                "invariants": "interval",
                "lib": "ppl",
                "pe_modes": [
                    4
                ],
                "pe_times": 1,
                "scc_depth": 5,
                "simplify_constraints": true,
                "termination": [
                    "qnlrfv1_1_1"
                ],
                "verbosity": 0
            },
            "cputime": 212.1673659999998,
            "date": "2018-09-15T20:46:44.845512",
            "memory": 0,
            "output": "NOT FOUND ",
            "status": "Unknown"
        },
        {
            "config": {
                "different_template": "iffail",
                "ei_out": false,
                "invariants": "interval",
                "lib": "ppl",
                "pe_modes": [
                    4
                ],
                "pe_times": 1,
                "scc_depth": 5,
                "simplify_constraints": true,
                "termination": [
                    "qnlrfv1_1_1"
                ],
                "verbosity": 0
            },
            "cputime": 305.59233799999936,
            "date": "2018-09-15T20:56:59.160113",
            "memory": 0,
            "output": "TL",
            "status": "Time Limit"
        },
        {
            "config": {
                "different_template": "always",
                "ei_out": false,
                "invariants": "interval",
                "lib": "ppl",
                "pe_modes": [
                    4
                ],
                "pe_times": 1,
                "scc_depth": 5,
                "simplify_constraints": true,
                "termination": [
                    "qnlrfv1_1_1"
                ],
                "verbosity": 0
            },
            "cputime": 229.17577800000063,
            "date": "2018-09-15T21:04:38.254728",
            "memory": 0,
            "output": "NOT FOUND ",
            "status": "Unknown"
        },
        {
            "config": {
                "different_template": "never",
                "ei_out": false,
                "invariants": "interval",
                "lib": "ppl",
                "pe_modes": [
                    4
                ],
                "pe_times": 1,
                "scc_depth": 5,
                "simplify_constraints": true,
                "termination": [
                    "qnlrfv1_2_2"
                ],
                "verbosity": 0
            },
            "cputime": 305.7955649999996,
            "date": "2018-09-15T21:14:51.878824",
            "memory": 0,
            "output": "TL",
            "status": "Time Limit"
        },
        {
            "config": {
                "different_template": "iffail",
                "ei_out": false,
                "invariants": "interval",
                "lib": "ppl",
                "pe_modes": [
                    4
                ],
                "pe_times": 1,
                "scc_depth": 5,
                "simplify_constraints": true,
                "termination": [
                    "qnlrfv1_2_2"
                ],
                "verbosity": 0
            },
            "cputime": 305.728106,
            "date": "2018-09-15T21:25:06.370574",
            "memory": 0,
            "output": "TL",
            "status": "Time Limit"
        },
        {
            "config": {
                "different_template": "always",
                "ei_out": false,
                "invariants": "interval",
                "lib": "ppl",
                "pe_modes": [
                    4
                ],
                "pe_times": 1,
                "scc_depth": 5,
                "simplify_constraints": true,
                "termination": [
                    "qnlrfv1_2_2"
                ],
                "verbosity": 0
            },
            "cputime": 305.7245460000007,
            "date": "2018-09-15T21:35:20.795912",
            "memory": 0,
            "output": "TL",
            "status": "Time Limit"
        },
        {
            "config": {
                "different_template": "never",
                "ei_out": false,
                "invariants": "interval",
                "lib": "ppl",
                "pe_modes": [
                    4
                ],
                "pe_times": 1,
                "scc_depth": 5,
                "simplify_constraints": true,
                "termination": [
                    "lrf_pr"
                ],
                "verbosity": 0
            },
            "cputime": 73.52758800000042,
            "date": "2018-09-15T21:37:48.690379",
            "memory": 0,
            "output": "NOT FOUND ",
            "status": "Unknown"
        },
        {
            "config": {
                "different_template": "iffail",
                "ei_out": false,
                "invariants": "interval",
                "lib": "ppl",
                "pe_modes": [
                    4
                ],
                "pe_times": 1,
                "scc_depth": 5,
                "simplify_constraints": true,
                "termination": [
                    "lrf_pr"
                ],
                "verbosity": 0
            },
            "cputime": 106.80227200000044,
            "date": "2018-09-15T21:41:23.704630",
            "memory": 0,
            "output": "NOT FOUND ",
            "status": "Unknown"
        },
        {
            "config": {
                "different_template": "always",
                "ei_out": false,
                "invariants": "interval",
                "lib": "ppl",
                "pe_modes": [
                    4
                ],
                "pe_times": 1,
                "scc_depth": 5,
                "simplify_constraints": true,
                "termination": [
                    "lrf_pr"
                ],
                "verbosity": 0
            },
            "cputime": 72.4286100000009,
            "date": "2018-09-15T21:43:49.314449",
            "memory": 0,
            "output": "NOT FOUND ",
            "status": "Unknown"
        },
        {
            "config": {
                "different_template": "never",
                "ei_out": false,
                "invariants": "interval",
                "lib": "ppl",
                "pe_modes": [
                    4
                ],
                "pe_times": 1,
                "scc_depth": 5,
                "simplify_constraints": true,
                "termination": [
                    "qnlrfv1_1_1"
                ],
                "verbosity": 0
            },
            "cputime": 212.99302499999925,
            "date": "2018-09-15T21:50:56.174711",
            "memory": 0,
            "output": "NOT FOUND ",
            "status": "Unknown"
        },
        {
            "config": {
                "different_template": "iffail",
                "ei_out": false,
                "invariants": "interval",
                "lib": "ppl",
                "pe_modes": [
                    4
                ],
                "pe_times": 1,
                "scc_depth": 5,
                "simplify_constraints": true,
                "termination": [
                    "qnlrfv1_1_1"
                ],
                "verbosity": 0
            },
            "cputime": 305.1160229999997,
            "date": "2018-09-15T22:01:08.437431",
            "memory": 0,
            "output": "TL",
            "status": "Time Limit"
        },
        {
            "config": {
                "different_template": "always",
                "ei_out": false,
                "invariants": "interval",
                "lib": "ppl",
                "pe_modes": [
                    4
                ],
                "pe_times": 1,
                "scc_depth": 5,
                "simplify_constraints": true,
                "termination": [
                    "qnlrfv1_1_1"
                ],
                "verbosity": 0
            },
            "cputime": 232.43229700000043,
            "date": "2018-09-15T22:08:54.078345",
            "memory": 0,
            "output": "NOT FOUND ",
            "status": "Unknown"
        },
        {
            "config": {
                "different_template": "never",
                "ei_out": false,
                "invariants": "interval",
                "lib": "ppl",
                "pe_modes": [
                    4
                ],
                "pe_times": 1,
                "scc_depth": 5,
                "simplify_constraints": true,
                "termination": [
                    "qnlrfv1_2_2"
                ],
                "verbosity": 0
            },
            "cputime": 305.73972199999986,
            "date": "2018-09-15T22:19:08.898612",
            "memory": 0,
            "output": "TL",
            "status": "Time Limit"
        },
        {
            "config": {
                "different_template": "iffail",
                "ei_out": false,
                "invariants": "interval",
                "lib": "ppl",
                "pe_modes": [
                    4
                ],
                "pe_times": 1,
                "scc_depth": 5,
                "simplify_constraints": true,
                "termination": [
                    "qnlrfv1_2_2"
                ],
                "verbosity": 0
            },
            "cputime": 305.7848179999996,
            "date": "2018-09-15T22:29:23.051011",
            "memory": 0,
            "output": "TL",
            "status": "Time Limit"
        },
        {
            "config": {
                "different_template": "always",
                "ei_out": false,
                "invariants": "interval",
                "lib": "ppl",
                "pe_modes": [
                    4
                ],
                "pe_times": 1,
                "scc_depth": 5,
                "simplify_constraints": true,
                "termination": [
                    "qnlrfv1_2_2"
                ],
                "verbosity": 0
            },
            "cputime": 305.5056369999995,
            "date": "2018-09-15T22:39:37.076910",
            "memory": 0,
            "output": "TL",
            "status": "Time Limit"
        },
        {
            "config": {
                "different_template": "never",
                "ei_out": false,
                "invariants": "polyhedra",
                "lib": "ppl",
                "pe_modes": [
                    4
                ],
                "pe_times": 1,
                "scc_depth": 5,
                "simplify_constraints": true,
                "termination": [
                    "lrf_pr"
                ],
                "verbosity": 0
            },
            "cputime": 68.78516099999996,
            "date": "2018-09-15T22:41:55.254730",
            "memory": 0,
            "output": "NOT FOUND ",
            "status": "Unknown"
        },
        {
            "config": {
                "different_template": "iffail",
                "ei_out": false,
                "invariants": "polyhedra",
                "lib": "ppl",
                "pe_modes": [
                    4
                ],
                "pe_times": 1,
                "scc_depth": 5,
                "simplify_constraints": true,
                "termination": [
                    "lrf_pr"
                ],
                "verbosity": 0
            },
            "cputime": 105.79922599999995,
            "date": "2018-09-15T22:45:28.426728",
            "memory": 0,
            "output": "NOT FOUND ",
            "status": "Unknown"
        },
        {
            "config": {
                "different_template": "always",
                "ei_out": false,
                "invariants": "polyhedra",
                "lib": "ppl",
                "pe_modes": [
                    4
                ],
                "pe_times": 1,
                "scc_depth": 5,
                "simplify_constraints": true,
                "termination": [
                    "lrf_pr"
                ],
                "verbosity": 0
            },
            "cputime": 72.79186499999963,
            "date": "2018-09-15T22:47:54.330718",
            "memory": 0,
            "output": "NOT FOUND ",
            "status": "Unknown"
        },
        {
            "config": {
                "different_template": "never",
                "ei_out": false,
                "invariants": "polyhedra",
                "lib": "ppl",
                "pe_modes": [
                    4
                ],
                "pe_times": 1,
                "scc_depth": 5,
                "simplify_constraints": true,
                "termination": [
                    "qnlrfv1_1_1"
                ],
                "verbosity": 0
            },
            "cputime": 214.50099200000017,
            "date": "2018-09-15T22:55:02.174096",
            "memory": 0,
            "output": "NOT FOUND ",
            "status": "Unknown"
        },
        {
            "config": {
                "different_template": "iffail",
                "ei_out": false,
                "invariants": "polyhedra",
                "lib": "ppl",
                "pe_modes": [
                    4
                ],
                "pe_times": 1,
                "scc_depth": 5,
                "simplify_constraints": true,
                "termination": [
                    "qnlrfv1_1_1"
                ],
                "verbosity": 0
            },
            "cputime": 305.65582700000095,
            "date": "2018-09-15T23:05:15.998848",
            "memory": 0,
            "output": "TL",
            "status": "Time Limit"
        },
        {
            "config": {
                "different_template": "always",
                "ei_out": false,
                "invariants": "polyhedra",
                "lib": "ppl",
                "pe_modes": [
                    4
                ],
                "pe_times": 1,
                "scc_depth": 5,
                "simplify_constraints": true,
                "termination": [
                    "qnlrfv1_1_1"
                ],
                "verbosity": 0
            },
            "cputime": 229.09841300000002,
            "date": "2018-09-15T23:12:55.270304",
            "memory": 0,
            "output": "NOT FOUND ",
            "status": "Unknown"
        },
        {
            "config": {
                "different_template": "never",
                "ei_out": false,
                "invariants": "polyhedra",
                "lib": "ppl",
                "pe_modes": [
                    4
                ],
                "pe_times": 1,
                "scc_depth": 5,
                "simplify_constraints": true,
                "termination": [
                    "qnlrfv1_2_2"
                ],
                "verbosity": 0
            },
            "cputime": 304.46233400000057,
            "date": "2018-09-15T23:23:06.578568",
            "memory": 0,
            "output": "TL",
            "status": "Time Limit"
        },
        {
            "config": {
                "different_template": "iffail",
                "ei_out": false,
                "invariants": "polyhedra",
                "lib": "ppl",
                "pe_modes": [
                    4
                ],
                "pe_times": 1,
                "scc_depth": 5,
                "simplify_constraints": true,
                "termination": [
                    "qnlrfv1_2_2"
                ],
                "verbosity": 0
            },
            "cputime": 305.6998299999979,
            "date": "2018-09-15T23:33:25.321652",
            "memory": 0,
            "output": "TL",
            "status": "Time Limit"
        },
        {
            "config": {
                "different_template": "always",
                "ei_out": false,
                "invariants": "polyhedra",
                "lib": "ppl",
                "pe_modes": [
                    4
                ],
                "pe_times": 1,
                "scc_depth": 5,
                "simplify_constraints": true,
                "termination": [
                    "qnlrfv1_2_2"
                ],
                "verbosity": 0
            },
            "cputime": 305.9096019999978,
            "date": "2018-09-15T23:43:39.162338",
            "memory": 556,
            "output": "TL",
            "status": "Time Limit"
        },
        {
            "config": {
                "different_template": "never",
                "ei_out": false,
                "invariants": "polyhedra",
                "lib": "ppl",
                "pe_modes": [
                    4
                ],
                "pe_times": 1,
                "scc_depth": 5,
                "simplify_constraints": true,
                "termination": [
                    "lrf_pr"
                ],
                "verbosity": 0
            },
            "cputime": 69.69032700000146,
            "date": "2018-09-15T23:45:59.422384",
            "memory": 0,
            "output": "NOT FOUND ",
            "status": "Unknown"
        },
        {
            "config": {
                "different_template": "iffail",
                "ei_out": false,
                "invariants": "polyhedra",
                "lib": "ppl",
                "pe_modes": [
                    4
                ],
                "pe_times": 1,
                "scc_depth": 5,
                "simplify_constraints": true,
                "termination": [
                    "lrf_pr"
                ],
                "verbosity": 0
            },
            "cputime": 107.63038700000115,
            "date": "2018-09-15T23:49:36.562257",
            "memory": 0,
            "output": "NOT FOUND ",
            "status": "Unknown"
        },
        {
            "config": {
                "different_template": "always",
                "ei_out": false,
                "invariants": "polyhedra",
                "lib": "ppl",
                "pe_modes": [
                    4
                ],
                "pe_times": 1,
                "scc_depth": 5,
                "simplify_constraints": true,
                "termination": [
                    "lrf_pr"
                ],
                "verbosity": 0
            },
            "cputime": 74.83898800000009,
            "date": "2018-09-15T23:52:10.258545",
            "memory": 0,
            "output": "NOT FOUND ",
            "status": "Unknown"
        },
        {
            "config": {
                "different_template": "never",
                "ei_out": false,
                "invariants": "polyhedra",
                "lib": "ppl",
                "pe_modes": [
                    4
                ],
                "pe_times": 1,
                "scc_depth": 5,
                "simplify_constraints": true,
                "termination": [
                    "qnlrfv1_1_1"
                ],
                "verbosity": 0
            },
            "cputime": 223.2104099999987,
            "date": "2018-09-15T23:59:36.986313",
            "memory": 0,
            "output": "NOT FOUND ",
            "status": "Unknown"
        },
        {
            "config": {
                "different_template": "iffail",
                "ei_out": false,
                "invariants": "polyhedra",
                "lib": "ppl",
                "pe_modes": [
                    4
                ],
                "pe_times": 1,
                "scc_depth": 5,
                "simplify_constraints": true,
                "termination": [
                    "qnlrfv1_1_1"
                ],
                "verbosity": 0
            },
            "cputime": 305.9618059999988,
            "date": "2018-09-16T00:09:48.532372",
            "memory": 0,
            "output": "TL",
            "status": "Time Limit"
        },
        {
            "config": {
                "different_template": "always",
                "ei_out": false,
                "invariants": "polyhedra",
                "lib": "ppl",
                "pe_modes": [
                    4
                ],
                "pe_times": 1,
                "scc_depth": 5,
                "simplify_constraints": true,
                "termination": [
                    "qnlrfv1_1_1"
                ],
                "verbosity": 0
            },
            "cputime": 229.32060100000228,
            "date": "2018-09-16T00:17:28.982753",
            "memory": 0,
            "output": "NOT FOUND ",
            "status": "Unknown"
        },
        {
            "config": {
                "different_template": "never",
                "ei_out": false,
                "invariants": "polyhedra",
                "lib": "ppl",
                "pe_modes": [
                    4
                ],
                "pe_times": 1,
                "scc_depth": 5,
                "simplify_constraints": true,
                "termination": [
                    "qnlrfv1_2_2"
                ],
                "verbosity": 0
            },
            "cputime": 305.9997430000002,
            "date": "2018-09-16T00:27:44.190535",
            "memory": 0,
            "output": "TL",
            "status": "Time Limit"
        },
        {
            "config": {
                "different_template": "iffail",
                "ei_out": false,
                "invariants": "polyhedra",
                "lib": "ppl",
                "pe_modes": [
                    4
                ],
                "pe_times": 1,
                "scc_depth": 5,
                "simplify_constraints": true,
                "termination": [
                    "qnlrfv1_2_2"
                ],
                "verbosity": 0
            },
            "cputime": 305.7886270000002,
            "date": "2018-09-16T00:37:58.145843",
            "memory": 0,
            "output": "TL",
            "status": "Time Limit"
        },
        {
            "config": {
                "different_template": "always",
                "ei_out": false,
                "invariants": "polyhedra",
                "lib": "ppl",
                "pe_modes": [
                    4
                ],
                "pe_times": 1,
                "scc_depth": 5,
                "simplify_constraints": true,
                "termination": [
                    "qnlrfv1_2_2"
                ],
                "verbosity": 0
            },
            "cputime": 305.31028100000077,
            "date": "2018-09-16T00:48:09.959234",
            "memory": 0,
            "output": "TL",
            "status": "Time Limit"
        }
    ],
    "file": "smt2/From_T2/f/fun7.t2_fixed.smt2",
    "id": "smt2_From_T2_f_fun7.t2_fixed.smt2"
}